{"creator":"admin","id":1,"isEditable":false,"isPublic":false,"name":"Roue de base","objectives":[{"description":"","id":1,"isEditable":false,"name":"Gagner avec \u003e 65% poss","period":1},{"description":"","id":2,"isEditable":false,"name":"Gagner avec \u003c 35% poss","period":1},{"description":"","id":3,"isEditable":false,"name":"Marquer un doublé","period":3},{"description":"","id":4,"isEditable":false,"name":"Gagner sans la touche rond","period":3},{"description":"","id":5,"isEditable":false,"name":"Gagner sans la touche croix","period":3},{"description":"","id":6,"isEditable":false,"name":"Gagner sans la touche triangle","period":3},{"description":"","id":7,"isEditable":false,"name":"Gagner sans la touche carré","period":3},{"description":"","id":8,"isEditable":false,"name":"Marquer 1 but de volée","period":3},{"description":"","id":9,"isEditable":false,"name":"Marquer 1 but de la tête","period":3},{"description":"","id":10,"isEditable":false,"name":"Marquer 1 penalty","period":3},{"description":"","id":11,"isEditable":false,"name":"Arreter 1 penalty","period":3},{"description":"","id":12,"isEditable":false,"name":"15 passes dans le camp adverse avant de marquer","period":3},{"description":"","id":13,"isEditable":false,"name":"Gagner sans la touche R2","period":3},{"description":"","id":14,"isEditable":false,"name":"Gagner sans la touche L2","period":3},{"description":"","id":15,"isEditable":false,"name":"Gagner sans la touche R1","period":3},{"description":"","id":16,"isEditable":false,"name":"Gagner sans la touche L1","period":3},{"description":"","id":17,"isEditable":false,"name":"Obtenir 4 corners","period":3},{"description":"","id":18,"isEditable":false,"name":"Marquer sur coup franc direct","period":3},{"description":"","id":19,"isEditable":false,"name":"Faire 0 faute en taclant au moins 3 fois","period":3},{"description":"","id":20,"isEditable":false,"name":"Marquer dans les 15 premieres minutes","period":3},{"description":"","id":21,"isEditable":false,"name":"Marquer dans les 15 dernieres minutes","period":3},{"description":"","id":22,"isEditable":false,"name":"Marquer avec un defenseur (placé defenseur)","period":3},{"description":"","id":23,"isEditable":false,"name":"Marquer en eliminant le gardien","period":3},{"description":"","id":24,"isEditable":false,"name":"Marquer de l\u0027exterieur de la surface","period":3},{"description":"","id":25,"isEditable":false,"name":"Marquer du mauvais pied","period":3},{"description":"","id":26,"isEditable":false,"name":"Se faire arreter un penalty","period":3},{"description":"","id":27,"isEditable":false,"name":"Ne concéder aucun tir","period":3},{"description":"","id":28,"isEditable":false,"name":"Marquer en moins de 5 passes","period":3},{"description":"","id":30,"isEditable":false,"name":"Provoquer un but contre son camp","period":3},{"description":"","id":29,"isEditable":false,"name":"Marquer avec action en une touche de balle a partir du camp adverse","period":3}]}